geizhals/__init__.py
geizhals/geizhals.py
geizhals-0.0.4.dist-info/METADATA
geizhals-0.0.4.dist-info/RECORD
geizhals-0.0.4.dist-info/WHEEL
geizhals-0.0.4.dist-info/top_level.txt
