Metadata-Version: 2.1
Name: geizhals
Version: 0.0.4
Summary: A parser for the Geizhals.eu website.
Home-page: https://github.com/JulianKahnert/PyGeizhals
Author: Julian Kahnert
Author-email: mail@juliankahnert.de
License: UNKNOWN
Platform: UNKNOWN
Classifier: Programming Language :: Python :: 3
Classifier: License :: OSI Approved :: Apache Software License
Classifier: Operating System :: OS Independent
Requires-Dist: beautifulsoup4 (>=4.6.3)
Requires-Dist: requests (>=2.19.1)
